nearorder/__init__.py
nearorder/bisect.py
nearorder/bisect_fallback.py
nearorder/filter.py
nearorder/types.py
nearorder/math/__init__.py
nearorder/math/generate.py
nearorder/math/metrics.py
nearorder-0.1.2.dist-info/licenses/DUAL-LICENSE
nearorder-0.1.2.dist-info/licenses/LICENSE
nearorder-0.1.2.dist-info/METADATA
nearorder-0.1.2.dist-info/WHEEL
nearorder-0.1.2.dist-info/top_level.txt
nearorder-0.1.2.dist-info/RECORD
