Metadata-Version: 2.4
Name: nearorder
Version: 0.1.2
Summary: Utilities for working with near-ordered sequences under bounded disorder.
Author-email: Kaoru <shiinasama2001@gmail.com>
License-Expression: MIT
Project-URL: Homepage, https://github.com/SHIINASAMA/nearorder
Project-URL: Repository, https://github.com/SHIINASAMA/nearorder
Project-URL: Issues, https://github.com/SHIINASAMA/nearorder/issues
Requires-Python: >=3.8
License-File: LICENSE
License-File: DUAL-LICENSE
Dynamic: license-file
